dmppred/blast_binaries/linux/blastp
dmppred/blast_binaries/mac/blastp
dmppred/blast_binaries/windows/blastp.exe
dmppred/blast_binaries/windows/nghttp2.dll
dmppred/blast_db/train.phr
dmppred/blast_db/train.pin
dmppred/blast_db/train.pog
dmppred/blast_db/train.psd
dmppred/blast_db/train.psi
dmppred/blast_db/train.psq
dmppred/model/diabetes_model_150f.onnx
dmppred/python_scripts/__init__.py
dmppred/python_scripts/dmppred.py
dmppred-1.2.5.dist-info/METADATA
dmppred-1.2.5.dist-info/WHEEL
dmppred-1.2.5.dist-info/entry_points.txt
dmppred-1.2.5.dist-info/top_level.txt
dmppred-1.2.5.dist-info/RECORD
