Metadata-Version: 2.1
Name: dmppred
Version: 1.2.5
Summary: Dmppred: A tool for predicting, designing, and scanning Type 1 associated peptides
Home-page: https://gitlab.com/raghavalab/dmppred
Author: Nishant Kumar
Author-email: nishantk@iiitd.ac.in
Requires-Python: >=3.6
Requires-Dist: numpy
Requires-Dist: pandas
Requires-Dist: scikit-learn
Requires-Dist: argparse
Requires-Dist: onnxruntime
